hadlib/__init__.py
hadlib/cli.py
hadlib/linux.cfg
Headers_as_Dependencies-0.1.1.dist-info/LICENCE
Headers_as_Dependencies-0.1.1.dist-info/METADATA
Headers_as_Dependencies-0.1.1.dist-info/WHEEL
Headers_as_Dependencies-0.1.1.dist-info/entry_points.txt
Headers_as_Dependencies-0.1.1.dist-info/top_level.txt
Headers_as_Dependencies-0.1.1.dist-info/RECORD
