Metadata-Version: 2.1
Name: Headers-as-Dependencies
Version: 0.1.1
Summary: Generate command-line options for C compiler from used headers
Home-page: https://github.com/fpom/had
Author: Franck Pommereau
Author-email: franck.pommereau@univ-evry.fr
License: UNKNOWN
Platform: UNKNOWN
Classifier: Development Status :: 4 - Beta
Classifier: Intended Audience :: Developers
Classifier: Topic :: Software Development :: Compilers
Classifier: License :: OSI Approved :: GNU General Public License (GPL)
Classifier: Programming Language :: Python :: 3.7
Classifier: Operating System :: OS Independent
Requires-Python: >=3.7
